accelbyte_py_sdk/services/auth/__init__.py
accelbyte_py_sdk/services/auth/_jwt.py
accelbyte_py_sdk/services/auth/_login.py
accelbyte_py_sdk/services/auth/_utils.py
accelbyte_py_sdk_feat_auth-0.3.0.dist-info/METADATA
accelbyte_py_sdk_feat_auth-0.3.0.dist-info/WHEEL
accelbyte_py_sdk_feat_auth-0.3.0.dist-info/top_level.txt
accelbyte_py_sdk_feat_auth-0.3.0.dist-info/RECORD
