Metadata-Version: 2.4
Name: accelbyte-py-sdk-feat-auth
Version: 0.3.0
Summary: AccelByte Python SDK - Feature - Auth
Requires-Python: >=3.9
Requires-Dist: PyJWT[crypto]
Requires-Dist: accelbyte-py-sdk-core
Requires-Dist: accelbyte-py-sdk-service-iam
